framegrab/__init__.py
framegrab/cli/__init__.py
framegrab/cli/autodiscover.py
framegrab/cli/clitools.py
framegrab/cli/main.py
framegrab/cli/preview.py
framegrab/config.py
framegrab/exceptions.py
framegrab/grabber.py
framegrab/motion.py
framegrab/ros2_client.py
framegrab/rtsp_discovery.py
framegrab/rtsp_server.py
framegrab/unavailable_module.py
framegrab-0.14.2.dist-info/METADATA
framegrab-0.14.2.dist-info/WHEEL
framegrab-0.14.2.dist-info/entry_points.txt
framegrab-0.14.2.dist-info/licenses/LICENSE.txt
framegrab-0.14.2.dist-info/RECORD
