Metadata-Version: 2.4
Name: framegrab
Version: 0.14.2
Summary: Easily grab frames from cameras or streams
License: MIT
License-File: LICENSE.txt
Author: Groundlight
Author-email: info@groundlight.ai
Requires-Python: >=3.9,<4.0
Classifier: License :: OSI Approved :: MIT License
Classifier: Programming Language :: Python :: 3
Classifier: Programming Language :: Python :: 3.9
Classifier: Programming Language :: Python :: 3.10
Classifier: Programming Language :: Python :: 3.11
Classifier: Programming Language :: Python :: 3.12
Classifier: Programming Language :: Python :: 3.13
Classifier: Programming Language :: Python :: 3.14
Provides-Extra: all
Provides-Extra: basler
Provides-Extra: raspberrypi
Provides-Extra: realsense
Provides-Extra: youtube
Requires-Dist: ascii-magic (==2.3)
Requires-Dist: click (>=8.1.6,<9.0.0)
Requires-Dist: imgcat (>=0.5.0,<0.6.0)
Requires-Dist: onvif-zeep (>=0.2.12,<0.3.0)
Requires-Dist: opencv-python (>=4.4.0.46,<5.0.0.0)
Requires-Dist: picamera2 (>=0.3.21) ; extra == "raspberrypi" or extra == "all"
Requires-Dist: pydantic (>=2.9.2,<3.0.0)
Requires-Dist: pypylon (>=4.1.0,<5.0.0) ; extra == "basler" or extra == "all"
Requires-Dist: pyrealsense2 (>=2.55.1.6486,<3.0.0.0) ; extra == "realsense" or extra == "all"
Requires-Dist: pyyaml (>=6.0.2,<7.0.0)
Requires-Dist: streamlink (>=7.0.0,<8.0.0) ; extra == "youtube" or extra == "all"
Requires-Dist: wsdiscovery (>=2.0.0,<3.0.0)
Project-URL: Homepage, https://www.groundlight.ai/
Project-URL: Repository, https://github.com/groundlight/framegrab
